fourier_johansen/__init__.py
fourier_johansen/critical_values.py
fourier_johansen/johansen.py
fourier_johansen/johansen_fourier.py
fourier_johansen/output.py
fourier_johansen/sbc_test.py
fourier_johansen/sc_vecm.py
fourier_johansen/union_test.py
fourier_johansen/utils.py
fourier_johansen-0.0.1.dist-info/licenses/LICENSE
fourier_johansen-0.0.1.dist-info/METADATA
fourier_johansen-0.0.1.dist-info/WHEEL
fourier_johansen-0.0.1.dist-info/top_level.txt
fourier_johansen-0.0.1.dist-info/RECORD
